orionstack/__init__.py
orionstack-0.0.1.dist-info/METADATA
orionstack-0.0.1.dist-info/WHEEL
orionstack-0.0.1.dist-info/top_level.txt
orionstack-0.0.1.dist-info/RECORD
