Metadata-Version: 2.4
Name: orionstack
Version: 0.0.1
Summary: OrionStack
Author: Afshawn Lotfi
License: MIT
Project-URL: Homepage, https://github.com/OpenOrion/orionstack
Classifier: Development Status :: 1 - Planning
Classifier: Intended Audience :: Developers
Classifier: License :: OSI Approved :: MIT License
Classifier: Programming Language :: Python :: 3
Classifier: Programming Language :: Python :: 3.10
Classifier: Programming Language :: Python :: 3.11
Classifier: Programming Language :: Python :: 3.12
Requires-Python: >=3.10
